hvac-stubs/METADATA.toml
hvac-stubs/__init__.pyi
hvac-stubs/adapters.pyi
hvac-stubs/aws_utils.pyi
hvac-stubs/exceptions.pyi
hvac-stubs/py.typed
hvac-stubs/utils.pyi
hvac-stubs/api/__init__.pyi
hvac-stubs/api/vault_api_base.pyi
hvac-stubs/api/vault_api_category.pyi
hvac-stubs/api/auth_methods/__init__.pyi
hvac-stubs/api/auth_methods/approle.pyi
hvac-stubs/api/auth_methods/aws.pyi
hvac-stubs/api/auth_methods/azure.pyi
hvac-stubs/api/auth_methods/cert.pyi
hvac-stubs/api/auth_methods/gcp.pyi
hvac-stubs/api/auth_methods/github.pyi
hvac-stubs/api/auth_methods/jwt.pyi
hvac-stubs/api/auth_methods/kubernetes.pyi
hvac-stubs/api/auth_methods/ldap.pyi
hvac-stubs/api/auth_methods/legacy_mfa.pyi
hvac-stubs/api/auth_methods/oidc.pyi
hvac-stubs/api/auth_methods/okta.pyi
hvac-stubs/api/auth_methods/radius.pyi
hvac-stubs/api/auth_methods/token.pyi
hvac-stubs/api/auth_methods/userpass.pyi
hvac-stubs/api/secrets_engines/__init__.pyi
hvac-stubs/api/secrets_engines/active_directory.pyi
hvac-stubs/api/secrets_engines/aws.pyi
hvac-stubs/api/secrets_engines/azure.pyi
hvac-stubs/api/secrets_engines/consul.pyi
hvac-stubs/api/secrets_engines/database.pyi
hvac-stubs/api/secrets_engines/gcp.pyi
hvac-stubs/api/secrets_engines/identity.pyi
hvac-stubs/api/secrets_engines/kv.pyi
hvac-stubs/api/secrets_engines/kv_v1.pyi
hvac-stubs/api/secrets_engines/kv_v2.pyi
hvac-stubs/api/secrets_engines/ldap.pyi
hvac-stubs/api/secrets_engines/pki.pyi
hvac-stubs/api/secrets_engines/rabbitmq.pyi
hvac-stubs/api/secrets_engines/ssh.pyi
hvac-stubs/api/secrets_engines/transform.pyi
hvac-stubs/api/secrets_engines/transit.pyi
hvac-stubs/api/system_backend/__init__.pyi
hvac-stubs/api/system_backend/audit.pyi
hvac-stubs/api/system_backend/auth.pyi
hvac-stubs/api/system_backend/capabilities.pyi
hvac-stubs/api/system_backend/health.pyi
hvac-stubs/api/system_backend/init.pyi
hvac-stubs/api/system_backend/key.pyi
hvac-stubs/api/system_backend/leader.pyi
hvac-stubs/api/system_backend/lease.pyi
types_hvac-2.3.0.20250914.dist-info/licenses/LICENSE
types_hvac-2.3.0.20250914.dist-info/METADATA
types_hvac-2.3.0.20250914.dist-info/WHEEL
types_hvac-2.3.0.20250914.dist-info/top_level.txt
types_hvac-2.3.0.20250914.dist-info/RECORD
